[
  {
    "file": "src/main.c",
    "arguments": [
      "/usr/sbin/arm-none-eabi-gcc",
      "-mcpu=cortex-m0plus",
      "-mthumb",
      "-ffreestanding",
      "-O2",
      "-Wall",
      "-fdata-sections",
      "-ffunction-sections",
      "-isystem",
      "./include",
      "-c",
      "src/main.c",
      "-o",
      "build/main.c.o"
    ],
    "directory": "/home/kitten/Documents/PicoOS",
    "output": "build/main.c.o"
  },
  {
    "file": "src/boot/vectors.s",
    "arguments": [
      "/usr/sbin/arm-none-eabi-gcc",
      "-mcpu=cortex-m0plus",
      "-mthumb",
      "-O0",
      "-x",
      "assembler-with-cpp",
      "-c",
      "src/boot/vectors.s",
      "-o",
      "build/boot/vectors.s.o"
    ],
    "directory": "/home/kitten/Documents/PicoOS",
    "output": "build/boot/vectors.s.o"
  },
  {
    "file": "src/boot/reset.s",
    "arguments": [
      "/usr/sbin/arm-none-eabi-gcc",
      "-mcpu=cortex-m0plus",
      "-mthumb",
      "-O0",
      "-x",
      "assembler-with-cpp",
      "-c",
      "src/boot/reset.s",
      "-o",
      "build/boot/reset.s.o"
    ],
    "directory": "/home/kitten/Documents/PicoOS",
    "output": "build/boot/reset.s.o"
  },
  {
    "file": "src/boot/boot2.s",
    "arguments": [
      "/usr/sbin/arm-none-eabi-gcc",
      "-mcpu=cortex-m0plus",
      "-mthumb",
      "-O0",
      "-x",
      "assembler-with-cpp",
      "-c",
      "src/boot/boot2.s",
      "-o",
      "build/boot/boot2.s.o"
    ],
    "directory": "/home/kitten/Documents/PicoOS",
    "output": "build/boot/boot2.s.o"
  }
]